coder_music_cli-0.8.14.dist-info/licenses/LICENSE
music_cli/__init__.py
music_cli/__main__.py
music_cli/ai_tracks.py
music_cli/cli.py
music_cli/client.py
music_cli/config.py
music_cli/daemon.py
music_cli/hf_cache.py
music_cli/history.py
music_cli/model_manager.py
music_cli/youtube_history.py
music_cli/context/__init__.py
music_cli/context/mood.py
music_cli/context/temporal.py
music_cli/platform/__init__.py
music_cli/platform/ipc.py
music_cli/platform/paths.py
music_cli/platform/player_control.py
music_cli/player/__init__.py
music_cli/player/base.py
music_cli/player/ffplay.py
music_cli/sources/__init__.py
music_cli/sources/ai_generator.py
music_cli/sources/local.py
music_cli/sources/radio.py
music_cli/sources/youtube.py
music_cli/sources/ai_models/__init__.py
music_cli/sources/ai_models/audioldm_strategy.py
music_cli/sources/ai_models/bark_strategy.py
music_cli/sources/ai_models/model_config.py
music_cli/sources/ai_models/model_registry.py
music_cli/sources/ai_models/model_strategy.py
music_cli/sources/ai_models/musicgen_strategy.py
music_cli/sources/ai_models/progress_callback.py
music_cli/sources/ai_models/strategy_cache.py
coder_music_cli-0.8.14.dist-info/METADATA
coder_music_cli-0.8.14.dist-info/WHEEL
coder_music_cli-0.8.14.dist-info/entry_points.txt
coder_music_cli-0.8.14.dist-info/top_level.txt
coder_music_cli-0.8.14.dist-info/RECORD
