Metadata-Version: 2.4
Name: coder-music-cli
Version: 0.8.14
Summary: A command-line music application for coders with daemon support, radio streaming, and AI-generated music
Author-email: Luong Nguyen <luongnv89@gmail.com>
Maintainer-email: Luong Nguyen <luongnv89@gmail.com>
License-Expression: MIT
Project-URL: Homepage, https://github.com/luongnv89/music-cli
Project-URL: Repository, https://github.com/luongnv89/music-cli
Project-URL: Documentation, https://github.com/luongnv89/music-cli#readme
Project-URL: Issues, https://github.com/luongnv89/music-cli/issues
Project-URL: Changelog, https://github.com/luongnv89/music-cli/releases
Keywords: music,cli,daemon,radio,ai-music,focus,coding,background-music,lofi,productivity,media-keys,mpris,now-playing
Classifier: Development Status :: 3 - Alpha
Classifier: Environment :: Console
Classifier: Intended Audience :: Developers
Classifier: Operating System :: POSIX :: Linux
Classifier: Operating System :: MacOS
Classifier: Operating System :: Microsoft :: Windows
Classifier: Programming Language :: Python :: 3
Classifier: Programming Language :: Python :: 3.10
Classifier: Programming Language :: Python :: 3.11
Classifier: Programming Language :: Python :: 3.12
Classifier: Topic :: Multimedia :: Sound/Audio :: Players
Requires-Python: >=3.10
License-File: LICENSE
Requires-Dist: click>=8.0
Requires-Dist: tomli>=2.0; python_version < "3.11"
Requires-Dist: tomli-w>=1.0
Requires-Dist: pyobjc-framework-MediaPlayer>=10.0; sys_platform == "darwin"
Requires-Dist: dbus-next>=0.2.3; sys_platform == "linux"
Requires-Dist: winrt-Windows.Media.Playback>=2.0.0; sys_platform == "win32"
Provides-Extra: ai
Requires-Dist: torch>=2.0; extra == "ai"
Requires-Dist: transformers<4.51,>=4.31; extra == "ai"
Requires-Dist: diffusers>=0.15.0; extra == "ai"
Requires-Dist: scipy>=1.10; extra == "ai"
Requires-Dist: tqdm>=4.64; extra == "ai"
Requires-Dist: accelerate>=0.20; extra == "ai"
Provides-Extra: youtube
Requires-Dist: yt-dlp>=2023.1.0; extra == "youtube"
Provides-Extra: dev
Requires-Dist: pytest>=7.0; extra == "dev"
Requires-Dist: pytest-asyncio>=0.21; extra == "dev"
Requires-Dist: pytest-cov>=4.0; extra == "dev"
Requires-Dist: black>=23.0; extra == "dev"
Requires-Dist: ruff>=0.1; extra == "dev"
Requires-Dist: mypy>=1.0; extra == "dev"
Requires-Dist: bandit>=1.7; extra == "dev"
Requires-Dist: pre-commit>=3.0; extra == "dev"
Dynamic: license-file
